{"version":3,"kind":"Article","sha256":"4f3aff1f31e13df743f49edbd0c7ac064dc861c2b2d3daa79cdae54c74f0b30c","slug":"index","location":"/README.md","dependencies":[],"frontmatter":{"title":"Wavelet Cookbook","content_includes_title":false,"authors":[{"nameParsed":{"literal":"Project Pythia Community","given":"Project Pythia","family":"Community"},"name":"Project Pythia Community","url":"https://projectpythia.org/","id":"contributors-myst-generated-uid-0"}],"open_access":true,"license":{"content":{"id":"CC-BY-4.0","url":"https://creativecommons.org/licenses/by/4.0/","name":"Creative Commons Attribution 4.0 International","free":true,"CC":true},"code":{"id":"Apache-2.0","url":"https://opensource.org/licenses/Apache-2.0","name":"Apache License 2.0","free":true,"osi":true}},"github":"https://github.com/projectpythia/wavelet-cookbook","copyright":"2024","affiliations":[{"id":"UAlbany","name":"University at Albany (SUNY)","department":"Atmospheric and Environmental Sciences","url":"https://www.albany.edu/daes"},{"id":"CISL","name":"NSF National Center for Atmospheric Research","department":"Computational and Information Systems Lab","url":"https://www.cisl.ucar.edu"},{"id":"Unidata","name":"NSF Unidata","url":"https://www.unidata.ucar.edu"},{"id":"Argonne","name":"Argonne National Laboratory","department":"Environmental Science Division","url":"https://www.anl.gov/evs"},{"id":"CarbonPlan","name":"CarbonPlan","url":"https://carbonplan.org"},{"id":"NVIDIA","name":"NVIDIA Corporation","url":"https://www.nvidia.com/"}],"source_url":"https://github.com/projectpythia/wavelet-cookbook/blob/main/README.md","edit_url":"https://github.com/projectpythia/wavelet-cookbook/edit/main/README.md","thumbnail":"/wavelet-cookbook/build/thumbnail-5ceee4b4d1459ff4aa727955f387b7c0.png","exports":[{"format":"md","filename":"README.md","url":"/wavelet-cookbook/build/README-de11a9918f6adff10185cb57776c61ad.md"}]},"mdast":{"type":"root","children":[{"type":"block","children":[{"type":"image","url":"/wavelet-cookbook/build/thumbnail-5ceee4b4d1459ff4aa727955f387b7c0.png","alt":"thumbnail","width":300,"key":"OumgAz7jq1","urlSource":"thumbnail.png"},{"type":"paragraph","position":{"start":{"line":5,"column":1},"end":{"line":7,"column":1}},"children":[{"type":"link","url":"https://github.com/ProjectPythia/wavelet-cookbook/actions/workflows/nightly-build.yaml","position":{"start":{"line":5,"column":1},"end":{"line":5,"column":1}},"children":[{"type":"image","url":"/wavelet-cookbook/build/1eb59c50c19f27870403704314508d7a.svg","alt":"nightly-build","position":{"start":{"line":5,"column":1},"end":{"line":5,"column":1}},"key":"AldcVCxC9v","urlSource":"https://github.com/ProjectPythia/wavelet-cookbook/actions/workflows/nightly-build.yaml/badge.svg"}],"urlSource":"https://github.com/ProjectPythia/wavelet-cookbook/actions/workflows/nightly-build.yaml","error":true,"key":"yy44hu9LQ8"},{"type":"text","value":"\n","position":{"start":{"line":5,"column":1},"end":{"line":5,"column":1}},"key":"pzfK9yOnCR"},{"type":"link","url":"https://binder.projectpythia.org/v2/gh/ProjectPythia/wavelet-cookbook/main?labpath=notebooks","position":{"start":{"line":5,"column":1},"end":{"line":5,"column":1}},"children":[{"type":"image","url":"/wavelet-cookbook/build/31e3f387ea168934ca949c27e9927ea4.svg","alt":"Binder","position":{"start":{"line":5,"column":1},"end":{"line":5,"column":1}},"key":"ODq2vA7shC","urlSource":"https://binder.projectpythia.org/badge_logo.svg"}],"urlSource":"https://binder.projectpythia.org/v2/gh/ProjectPythia/wavelet-cookbook/main?labpath=notebooks","key":"j9irtXOc2X"},{"type":"text","value":"\n","position":{"start":{"line":5,"column":1},"end":{"line":5,"column":1}},"key":"WpFjo3qRDs"},{"type":"link","url":"https://doi.org/10.5281/zenodo.815311051","position":{"start":{"line":5,"column":1},"end":{"line":5,"column":1}},"children":[{"type":"image","url":"/wavelet-cookbook/build/14169c2ff017091d678f578d8d76811d.svg","alt":"DOI","position":{"start":{"line":5,"column":1},"end":{"line":5,"column":1}},"key":"HuELJhPDR6","urlSource":"https://zenodo.org/badge/815311051.svg"}],"urlSource":"https://zenodo.org/badge/latestdoi/815311051","data":{"doi":"10.5281/zenodo.815311051"},"internal":false,"protocol":"doi","key":"lDKeRlDjBu"}],"key":"XeycDL6mK6"},{"type":"paragraph","position":{"start":{"line":9,"column":1},"end":{"line":9,"column":1}},"children":[{"type":"text","value":"This Project Pythia Cookbook covers the background and how to work with wavelets in Python","position":{"start":{"line":9,"column":1},"end":{"line":9,"column":1}},"key":"LLoS44dZBD"}],"key":"JqtBVIuKfG"},{"type":"heading","depth":2,"position":{"start":{"line":11,"column":1},"end":{"line":11,"column":1}},"children":[{"type":"text","value":"Motivation","position":{"start":{"line":11,"column":1},"end":{"line":11,"column":1}},"key":"ytjSWCKUdw"}],"identifier":"motivation","label":"Motivation","html_id":"motivation","implicit":true,"key":"XzcecyOCCJ"},{"type":"paragraph","position":{"start":{"line":12,"column":1},"end":{"line":12,"column":1}},"children":[{"type":"text","value":"Wavelets are a powerful tool to analyze time-series data. When data frequencies vary over time, wavelets can be applied to analysis trends and overcome the time/frequency limitations of Fourier Transforms","position":{"start":{"line":12,"column":1},"end":{"line":12,"column":1}},"key":"gCM6turulq"}],"key":"P0ryZJRinl"},{"type":"heading","depth":2,"position":{"start":{"line":14,"column":1},"end":{"line":14,"column":1}},"children":[{"type":"text","value":"Authors","position":{"start":{"line":14,"column":1},"end":{"line":14,"column":1}},"key":"YTGp1xK7e8"}],"identifier":"authors","label":"Authors","html_id":"authors","implicit":true,"key":"S9zTyqT9dd"},{"type":"paragraph","position":{"start":{"line":16,"column":1},"end":{"line":16,"column":1}},"children":[{"type":"link","url":"https://github.com/cyschneck","position":{"start":{"line":16,"column":1},"end":{"line":16,"column":1}},"children":[{"type":"text","value":"Cora Schneck","position":{"start":{"line":16,"column":1},"end":{"line":16,"column":1}},"key":"BKlhaZpfiy"}],"urlSource":"https://github.com/cyschneck","error":true,"key":"uRs7ohnZUq"}],"key":"r2ygZcL5FL"},{"type":"heading","depth":3,"position":{"start":{"line":18,"column":1},"end":{"line":18,"column":1}},"children":[{"type":"text","value":"Contributors","position":{"start":{"line":18,"column":1},"end":{"line":18,"column":1}},"key":"LeHtwoCk8R"}],"identifier":"contributors","label":"Contributors","html_id":"contributors","implicit":true,"key":"ITHjc4yQlO"},{"type":"link","url":"https://github.com/ProjectPythia/wavelet-cookbook/graphs/contributors","children":[{"type":"image","url":"/wavelet-cookbook/build/3bb0f103e9077a8008c2d7f2f8c3d5b9.svg","key":"L2tEJzZiMy","urlSource":"https://contrib.rocks/image?repo=ProjectPythia/wavelet-cookbook"}],"urlSource":"https://github.com/ProjectPythia/wavelet-cookbook/graphs/contributors","error":true,"key":"NZIE0vWPwU"},{"type":"heading","depth":2,"position":{"start":{"line":24,"column":1},"end":{"line":24,"column":1}},"children":[{"type":"text","value":"Structure","position":{"start":{"line":24,"column":1},"end":{"line":24,"column":1}},"key":"ynSPfT3Rzv"}],"identifier":"structure","label":"Structure","html_id":"structure","implicit":true,"key":"vBR5i2U9gS"},{"type":"paragraph","position":{"start":{"line":26,"column":1},"end":{"line":26,"column":1}},"children":[{"type":"text","value":"This cookbook is broken into two main sections:","position":{"start":{"line":26,"column":1},"end":{"line":26,"column":1}},"key":"O46ZXLAGIg"}],"key":"E3CrsqC0To"},{"type":"list","ordered":false,"spread":false,"position":{"start":{"line":28,"column":1},"end":{"line":30,"column":1}},"children":[{"type":"listItem","spread":true,"position":{"start":{"line":28,"column":1},"end":{"line":28,"column":1}},"children":[{"type":"paragraph","children":[{"type":"text","value":"Introduction","position":{"start":{"line":28,"column":1},"end":{"line":28,"column":1}},"key":"iSYn42wEVi"}],"key":"fmkNeOhmdE"}],"key":"w71OULqB9b"},{"type":"listItem","spread":true,"position":{"start":{"line":29,"column":1},"end":{"line":30,"column":1}},"children":[{"type":"paragraph","children":[{"type":"text","value":"Example Geoscience Workflows","position":{"start":{"line":29,"column":1},"end":{"line":29,"column":1}},"key":"eyhAEeuHrl"}],"key":"JqM9rp0zoe"}],"key":"nj1RsjBGDA"}],"key":"bm6nwriRr6"},{"type":"heading","depth":3,"position":{"start":{"line":31,"column":1},"end":{"line":31,"column":1}},"children":[{"type":"text","value":"Introduction","position":{"start":{"line":31,"column":1},"end":{"line":31,"column":1}},"key":"o9IDq4R7JL"}],"identifier":"introduction","label":"Introduction","html_id":"introduction","implicit":true,"key":"lMDVbZYoxG"},{"type":"list","ordered":false,"spread":false,"position":{"start":{"line":33,"column":1},"end":{"line":36,"column":1}},"children":[{"type":"listItem","spread":true,"position":{"start":{"line":33,"column":1},"end":{"line":33,"column":1}},"children":[{"type":"paragraph","children":[{"type":"emphasis","position":{"start":{"line":33,"column":1},"end":{"line":33,"column":1}},"children":[{"type":"text","value":"“Wavelet Basics”","position":{"start":{"line":33,"column":1},"end":{"line":33,"column":1}},"key":"hJzwzRoibV"}],"key":"beSETHFITS"},{"type":"text","value":": Understand the motivation and background for wavelet analysis by reviewing time-series data and the strengths and weaknesses of other signal analysis tools like Fourier Transform","position":{"start":{"line":33,"column":1},"end":{"line":33,"column":1}},"key":"T2gV8RS2m2"}],"key":"oCSlPNyeKr"}],"key":"DEi0YNGFon"},{"type":"listItem","spread":true,"position":{"start":{"line":34,"column":1},"end":{"line":34,"column":1}},"children":[{"type":"paragraph","children":[{"type":"emphasis","position":{"start":{"line":34,"column":1},"end":{"line":34,"column":1}},"children":[{"type":"text","value":"“PyWavelets and Jingle Bells”","position":{"start":{"line":34,"column":1},"end":{"line":34,"column":1}},"key":"InWPDpbPbP"}],"key":"Yd0zI93mk3"},{"type":"text","value":": Learn how to use ","position":{"start":{"line":34,"column":1},"end":{"line":34,"column":1}},"key":"V5FXpXBlk6"},{"type":"inlineCode","value":"PyWavelets","position":{"start":{"line":34,"column":1},"end":{"line":34,"column":1}},"key":"qI18jrZLLG"},{"type":"text","value":", a Python implementation of wavelet analysis, to determine the order of notes in a simple musical piece","position":{"start":{"line":34,"column":1},"end":{"line":34,"column":1}},"key":"M5570TDKyK"}],"key":"h46UHu8PnN"}],"key":"GmQ683LxDS"},{"type":"listItem","spread":true,"position":{"start":{"line":35,"column":1},"end":{"line":36,"column":1}},"children":[{"type":"paragraph","children":[{"type":"emphasis","position":{"start":{"line":35,"column":1},"end":{"line":35,"column":1}},"children":[{"type":"text","value":"“Spy Keypad”","position":{"start":{"line":35,"column":1},"end":{"line":35,"column":1}},"key":"cI14DP0TG6"}],"key":"rCR7pSC9I8"},{"type":"text","value":": Learn how to use wavelets to undercover the frequency and order of notes in an unknown piece of audio data","position":{"start":{"line":35,"column":1},"end":{"line":35,"column":1}},"key":"v7PMkYaMgG"}],"key":"UkqTrS4AEe"}],"key":"eOIlkIlbAP"}],"key":"YxJS3prWgY"},{"type":"heading","depth":3,"position":{"start":{"line":37,"column":1},"end":{"line":37,"column":1}},"children":[{"type":"text","value":"Geoscience Workflows","position":{"start":{"line":37,"column":1},"end":{"line":37,"column":1}},"key":"GCv8YWK6pv"}],"identifier":"geoscience-workflows","label":"Geoscience Workflows","html_id":"geoscience-workflows","implicit":true,"key":"k696qqhQqJ"},{"type":"list","ordered":false,"spread":false,"position":{"start":{"line":39,"column":1},"end":{"line":41,"column":1}},"children":[{"type":"listItem","spread":true,"position":{"start":{"line":39,"column":1},"end":{"line":39,"column":1}},"children":[{"type":"paragraph","children":[{"type":"emphasis","position":{"start":{"line":39,"column":1},"end":{"line":39,"column":1}},"children":[{"type":"text","value":"“Atmospheric Data: Nino 3 SST Index”","position":{"start":{"line":39,"column":1},"end":{"line":39,"column":1}},"key":"Zt2afZQT18"}],"key":"zflns4B2kR"},{"type":"text","value":": Learn how to apply wavelets to real atmospheric and oceanic data to generate a power wavelet scalogram, similar to the 1999 paper ","position":{"start":{"line":39,"column":1},"end":{"line":39,"column":1}},"key":"WJFwDikSNz"},{"type":"link","url":"https://psl.noaa.gov/people/gilbert.p.compo/Torrence_compo1998.pdf","position":{"start":{"line":39,"column":1},"end":{"line":39,"column":1}},"children":[{"type":"text","value":"“A Practical Guide to Wavelet Analysis”","position":{"start":{"line":39,"column":1},"end":{"line":39,"column":1}},"key":"Dm1cvhfcRQ"}],"urlSource":"https://psl.noaa.gov/people/gilbert.p.compo/Torrence_compo1998.pdf","key":"KNHBRUptie"},{"type":"text","value":" by Torrence and Compo in Python","position":{"start":{"line":39,"column":1},"end":{"line":39,"column":1}},"key":"MDfuQY8XZq"}],"key":"eQn0uLdEeQ"}],"key":"MIYcAbbmAL"},{"type":"listItem","spread":true,"position":{"start":{"line":40,"column":1},"end":{"line":41,"column":1}},"children":[{"type":"paragraph","children":[{"type":"emphasis","position":{"start":{"line":40,"column":1},"end":{"line":40,"column":1}},"children":[{"type":"text","value":"“Buoys and Wave(let)s”","position":{"start":{"line":40,"column":1},"end":{"line":40,"column":1}},"key":"qyqTSccQHv"}],"key":"eT6iGPWvFA"},{"type":"text","value":": Apply wavelets to understand how wave heights and energy change over years of data with historical records from NOAA’s National Data Buoy Center","position":{"start":{"line":40,"column":1},"end":{"line":40,"column":1}},"key":"TiN6lgxYPb"}],"key":"WbhRrxgCZh"}],"key":"aCeZpcEDVw"}],"key":"jJvFKpvqXS"},{"type":"heading","depth":2,"position":{"start":{"line":42,"column":1},"end":{"line":42,"column":1}},"children":[{"type":"text","value":"Running the Notebooks","position":{"start":{"line":42,"column":1},"end":{"line":42,"column":1}},"key":"cgS50SHxFZ"}],"identifier":"running-the-notebooks","label":"Running the Notebooks","html_id":"running-the-notebooks","implicit":true,"key":"h78ox0DkqW"},{"type":"paragraph","position":{"start":{"line":44,"column":1},"end":{"line":44,"column":1}},"children":[{"type":"text","value":"You can either run the notebook using ","position":{"start":{"line":44,"column":1},"end":{"line":44,"column":1}},"key":"lnW1lLAHTE"},{"type":"link","url":"https://binder.projectpythia.org/","position":{"start":{"line":44,"column":1},"end":{"line":44,"column":1}},"children":[{"type":"text","value":"Binder","position":{"start":{"line":44,"column":1},"end":{"line":44,"column":1}},"key":"XJMwJOfDZY"}],"urlSource":"https://binder.projectpythia.org/","key":"EcOuxl6TDg"},{"type":"text","value":" or on your local machine.","position":{"start":{"line":44,"column":1},"end":{"line":44,"column":1}},"key":"jCVxKGuo8Q"}],"key":"uMAlQoTRCO"},{"type":"heading","depth":3,"position":{"start":{"line":46,"column":1},"end":{"line":46,"column":1}},"children":[{"type":"text","value":"Running on Binder","position":{"start":{"line":46,"column":1},"end":{"line":46,"column":1}},"key":"TeDCOxLysF"}],"identifier":"running-on-binder","label":"Running on Binder","html_id":"running-on-binder","implicit":true,"key":"uYp2D8shkG"},{"type":"paragraph","position":{"start":{"line":48,"column":1},"end":{"line":61,"column":1}},"children":[{"type":"text","value":"The simplest way to interact with a Jupyter Notebook is through\n","position":{"start":{"line":48,"column":1},"end":{"line":48,"column":1}},"key":"tccT5wRGMq"},{"type":"link","url":"https://binder.projectpythia.org/","position":{"start":{"line":48,"column":1},"end":{"line":48,"column":1}},"children":[{"type":"text","value":"Binder","position":{"start":{"line":48,"column":1},"end":{"line":48,"column":1}},"key":"xK4an7Jwkl"}],"urlSource":"https://binder.projectpythia.org/","key":"qwVk16WFDA"},{"type":"text","value":", which enables the execution of a\n","position":{"start":{"line":48,"column":1},"end":{"line":48,"column":1}},"key":"ijjCHuwzDf"},{"type":"link","url":"https://jupyterbook.org","position":{"start":{"line":48,"column":1},"end":{"line":48,"column":1}},"children":[{"type":"text","value":"Jupyter Book","position":{"start":{"line":48,"column":1},"end":{"line":48,"column":1}},"key":"Z2ANEPdMln"}],"urlSource":"https://jupyterbook.org","key":"rzjiTUmy2x"},{"type":"text","value":" in the cloud. The details of how this works are not\nimportant for now. All you need to know is how to launch a Pythia\nCookbooks chapter via Binder. Simply navigate your mouse to\nthe top right corner of the book chapter you are viewing and click\non the rocket ship icon, (see figure below), and be sure to select\n“launch Binder”. After a moment you should be presented with a\nnotebook that you can interact with. I.e. you’ll be able to execute\nand even change the example programs. You’ll see that the code cells\nhave no output at first, until you execute them by pressing\n","position":{"start":{"line":48,"column":1},"end":{"line":48,"column":1}},"key":"MlPzKwZWLe"},{"type":"keyboard","children":[{"type":"text","value":"Shift","key":"RWudaVZ4Qr"}],"key":"hsspOg8Ye9"},{"type":"text","value":"+","position":{"start":{"line":48,"column":1},"end":{"line":48,"column":1}},"key":"WxdLM0d8CA"},{"type":"keyboard","children":[{"type":"text","value":"Enter","key":"xOphHFlkQz"}],"key":"vFs9myaGFP"},{"type":"text","value":". Complete details on how to interact with\na live Jupyter notebook are described in ","position":{"start":{"line":48,"column":1},"end":{"line":48,"column":1}},"key":"YJot9GlrDn"},{"type":"link","url":"https://foundations.projectpythia.org/foundations/getting-started-jupyter","position":{"start":{"line":48,"column":1},"end":{"line":48,"column":1}},"children":[{"type":"text","value":"Getting Started with\nJupyter","position":{"start":{"line":48,"column":1},"end":{"line":48,"column":1}},"key":"LphwbMy70l"}],"urlSource":"https://foundations.projectpythia.org/foundations/getting-started-jupyter","key":"T33DhfbxcR"},{"type":"text","value":".","position":{"start":{"line":48,"column":1},"end":{"line":48,"column":1}},"key":"zkGCHDgcxF"}],"key":"hnLHjCMeMI"},{"type":"heading","depth":3,"position":{"start":{"line":63,"column":1},"end":{"line":63,"column":1}},"children":[{"type":"text","value":"Running on Your Own Machine","position":{"start":{"line":63,"column":1},"end":{"line":63,"column":1}},"key":"JSkIIQ2Mw1"}],"identifier":"running-on-your-own-machine","label":"Running on Your Own Machine","html_id":"running-on-your-own-machine","implicit":true,"key":"p8E28xJREa"},{"type":"paragraph","position":{"start":{"line":65,"column":1},"end":{"line":65,"column":1}},"children":[{"type":"text","value":"If you are interested in running this material locally on your computer, you will need to follow this workflow:","position":{"start":{"line":65,"column":1},"end":{"line":65,"column":1}},"key":"isMEhLkpEa"}],"key":"L36r3W4bVb"},{"type":"list","ordered":true,"start":1,"spread":false,"position":{"start":{"line":67,"column":1},"end":{"line":86,"column":1}},"children":[{"type":"listItem","spread":true,"position":{"start":{"line":67,"column":1},"end":{"line":72,"column":1}},"children":[{"type":"paragraph","position":{"start":{"line":67,"column":1},"end":{"line":67,"column":1}},"children":[{"type":"text","value":"Clone the ","position":{"start":{"line":67,"column":1},"end":{"line":67,"column":1}},"key":"yEAiT8B0dK"},{"type":"inlineCode","value":"https://github.com/ProjectPythia/wavelet-cookbook","position":{"start":{"line":67,"column":1},"end":{"line":67,"column":1}},"key":"AFDHbbNbtj"},{"type":"text","value":" repository:","position":{"start":{"line":67,"column":1},"end":{"line":67,"column":1}},"key":"xc9kGZsSZ3"}],"key":"lHJtG8FPBp"},{"type":"code","lang":"bash","value":" git clone https://github.com/ProjectPythia/wavelet-cookbook.git","position":{"start":{"line":69,"column":1},"end":{"line":71,"column":1}},"key":"ZjmwcwiBeE"}],"key":"VTy755JPMw"},{"type":"listItem","spread":true,"position":{"start":{"line":73,"column":1},"end":{"line":76,"column":1}},"children":[{"type":"paragraph","position":{"start":{"line":73,"column":1},"end":{"line":73,"column":1}},"children":[{"type":"text","value":"Move into the ","position":{"start":{"line":73,"column":1},"end":{"line":73,"column":1}},"key":"rqsnoY8M4f"},{"type":"inlineCode","value":"wavelet-cookbook","position":{"start":{"line":73,"column":1},"end":{"line":73,"column":1}},"key":"hJyipQP9f3"},{"type":"text","value":" directory","position":{"start":{"line":73,"column":1},"end":{"line":73,"column":1}},"key":"jnJHG1h6zc"}],"key":"zPcdnddUW3"},{"type":"code","lang":"bash","value":"cd wavelet-cookbook","position":{"start":{"line":74,"column":1},"end":{"line":76,"column":1}},"key":"XbCdvPNDf3"}],"key":"e85l66LGX1"},{"type":"listItem","spread":true,"position":{"start":{"line":77,"column":1},"end":{"line":81,"column":1}},"children":[{"type":"paragraph","position":{"start":{"line":77,"column":1},"end":{"line":77,"column":1}},"children":[{"type":"text","value":"Create and activate your conda environment from the ","position":{"start":{"line":77,"column":1},"end":{"line":77,"column":1}},"key":"BiGe34ECyR"},{"type":"inlineCode","value":"environment.yml","position":{"start":{"line":77,"column":1},"end":{"line":77,"column":1}},"key":"P27Q2OrPMo"},{"type":"text","value":" file","position":{"start":{"line":77,"column":1},"end":{"line":77,"column":1}},"key":"Y3mHEVDStk"}],"key":"LfXBAiSmSq"},{"type":"code","lang":"bash","value":"conda env create -f environment.yml\nconda activate cookbook-dev","position":{"start":{"line":78,"column":1},"end":{"line":81,"column":1}},"key":"y2SGr4WRh9"}],"key":"VtK65pvm07"},{"type":"listItem","spread":true,"position":{"start":{"line":82,"column":1},"end":{"line":86,"column":1}},"children":[{"type":"paragraph","position":{"start":{"line":82,"column":1},"end":{"line":82,"column":1}},"children":[{"type":"text","value":"Move into the ","position":{"start":{"line":82,"column":1},"end":{"line":82,"column":1}},"key":"ctqKg0CXFE"},{"type":"inlineCode","value":"notebooks","position":{"start":{"line":82,"column":1},"end":{"line":82,"column":1}},"key":"pxiQyf8dzj"},{"type":"text","value":" directory and start up Jupyterlab","position":{"start":{"line":82,"column":1},"end":{"line":82,"column":1}},"key":"ukI9MDe7g9"}],"key":"jN6HSkylgN"},{"type":"code","lang":"bash","value":"cd notebooks/\njupyter lab","position":{"start":{"line":83,"column":1},"end":{"line":86,"column":1}},"key":"TTuvRvweu1"}],"key":"SoNFOJDBwp"}],"key":"KbxCCx0V5d"}],"key":"XPvPtDwuWh"}],"key":"SSh2QYAOz6"},"references":{"cite":{"order":[],"data":{}}},"footer":{"navigation":{"next":{"title":"How to Cite This Cookbook","url":"/notebooks/how-to-cite","group":"Preamble"}}},"domain":"http://localhost:3000"}